zinnia_hashids/factory.py
zinnia_hashids/views.py
zinnia_hashids/urls.py
zinnia_hashids/__init__.py
zinnia_hashids/backend.py
zinnia_hashids/settings.py
zinnia_url_shortener_hashids-1.1.dist-info/metadata.json
zinnia_url_shortener_hashids-1.1.dist-info/top_level.txt
zinnia_url_shortener_hashids-1.1.dist-info/DESCRIPTION.rst
zinnia_url_shortener_hashids-1.1.dist-info/RECORD
zinnia_url_shortener_hashids-1.1.dist-info/METADATA
zinnia_url_shortener_hashids-1.1.dist-info/WHEEL
